sunpy_soar/__init__.py
sunpy_soar/_version.py
sunpy_soar/attrs.py
sunpy_soar/client.py
sunpy_soar/conftest.py
sunpy_soar/version.py
sunpy_soar/data/README.rst
sunpy_soar/data/attrs.json
sunpy_soar/data/instrument_attrs.json
sunpy_soar/data/soop_attrs.json
sunpy_soar/tests/__init__.py
sunpy_soar/tests/test_sunpy_soar.py
sunpy_soar-1.11.1.dist-info/LICENSE
sunpy_soar-1.11.1.dist-info/METADATA
sunpy_soar-1.11.1.dist-info/WHEEL
sunpy_soar-1.11.1.dist-info/top_level.txt
sunpy_soar-1.11.1.dist-info/RECORD
