Metadata-Version: 2.2
Name: sunpy_soar
Version: 1.11.1
Summary: A sunpy FIDO plugin for accessing data in the Solar Orbiter Archive (SOAR).
Author: David Stansby
Author-email: The SunPy Community <sunpy@googlegroups.com>
License: Copyright (c) 2024, The SunPy Community
Project-URL: Homepage, https://sunpy.org
Project-URL: Source Code, https://github.com/sunpy/sunpy-soar
Project-URL: Download, https://pypi.org/project/sunpy-soar
Project-URL: Documentation, https://docs.sunpy.org/projects/soar
Project-URL: Changelog, https://docs.sunpy.org/projects/soar/en/stable/whatsnew/changelog.html
Project-URL: Issue Tracker, https://github.com/sunpy/sunpy-soar/issues
Requires-Python: >=3.10
License-File: LICENSE
Requires-Dist: matplotlib>=3.6.0
Requires-Dist: astropy>=5.3.0
Requires-Dist: sunpy[net]>=6.0.0
Requires-Dist: requests>=2.28.0
Provides-Extra: tests
Requires-Dist: pytest-cov; extra == "tests"
Requires-Dist: pytest-doctestplus; extra == "tests"
Requires-Dist: pytest-xdist; extra == "tests"
Requires-Dist: pytest; extra == "tests"
Requires-Dist: responses>=0.20.0; extra == "tests"
Requires-Dist: sunpy[map,net]>=6.0.0; extra == "tests"
Provides-Extra: docs
Requires-Dist: sphinx; extra == "docs"
Requires-Dist: sphinx-automodapi; extra == "docs"
Requires-Dist: matplotlib; extra == "docs"
Requires-Dist: sphinx-changelog; extra == "docs"
Requires-Dist: sphinx-copybutton; extra == "docs"
Requires-Dist: sphinx-gallery; extra == "docs"
Requires-Dist: sphinxext-opengraph; extra == "docs"
Requires-Dist: sunpy-sphinx-theme; extra == "docs"
Provides-Extra: dev
Requires-Dist: sunpy-soar[docs,tests]; extra == "dev"
